aiml/__init__.py
aiml/attack/__init__.py
aiml/attack/adversarial_attacks.py
aiml/attack/attack_evaluation.py
aiml/evaluation/__init__.py
aiml/evaluation/check_accuracy.py
aiml/evaluation/dynamic.py
aiml/evaluation/evaluate.py
aiml/load_data/__init__.py
aiml/load_data/generate_parameter.py
aiml/load_data/load_model.py
aiml/load_data/load_set.py
aiml/load_data/normalize_datasets.py
aiml/surrogate_model/__init__.py
aiml/surrogate_model/create_surrogate_model.py
aiml/surrogate_model/models.py
aiml/surrogate_model/utils.py
adversarial_insight_ml-0.2.2.dist-info/LICENSE
adversarial_insight_ml-0.2.2.dist-info/METADATA
adversarial_insight_ml-0.2.2.dist-info/WHEEL
adversarial_insight_ml-0.2.2.dist-info/top_level.txt
adversarial_insight_ml-0.2.2.dist-info/RECORD
