Metadata-Version: 2.1
Name: adversarial-insight-ml
Version: 0.2.2
Author-email: Sungjae Jang <sjan260@aucklanduni.ac.nz>, Takuya Saegusa <tsae032@aucklanduni.ac.nz>, Haozhe Wei <hwei313@aucklanduni.ac.nz>, Terence Zhang <tzha820@aucklanduni.ac.nz>, Yuming Zhou <yzho739@aucklanduni.ac.nz>, Luke Chang <luke.x.chang@gmail.com>
License: MIT License
Classifier: Programming Language :: Python :: 3
Classifier: Programming Language :: Python :: 3.8
Classifier: Programming Language :: Python :: 3.9
Classifier: Programming Language :: Python :: 3.10
Classifier: Programming Language :: Python :: 3.11
Requires-Python: >=3.8
License-File: LICENSE
Requires-Dist: adversarial-robustness-toolbox
Requires-Dist: torch
Requires-Dist: detectors
Requires-Dist: lightning
Requires-Dist: torchmetrics
Requires-Dist: datasets
Provides-Extra: dev
Requires-Dist: autopep8 ; extra == 'dev'
Requires-Dist: bumpver ; extra == 'dev'
Requires-Dist: pytest ; extra == 'dev'
Requires-Dist: sphinx ; extra == 'dev'
Requires-Dist: sphinx-rtd-theme ; extra == 'dev'
Requires-Dist: scikit-learn ; extra == 'dev'
Requires-Dist: jupyterlab ; extra == 'dev'
Requires-Dist: pip-tools ; extra == 'dev'
